{
  "swagger": "2.0",
  "info": {
    "version": "1.0.0",
    "title": "REST API",
    "description": ""
  },
  "host": "localhost:3000",
  "basePath": "/",
  "schemes": [
    "http"
  ],
  "paths": {
    "/": {
      "get": {
        "description": "",
        "parameters": [],
        "responses": {
          "200": {
            "description": "OK"
          }
        }
      }
    },
    "/weather/detailsByCity": {
      "get": {
        "description": "",
        "parameters": [
          {
            "name": "city",
            "in": "query",
            "type": "string"
          },
          {
            "name": "units",
            "in": "query",
            "type": "string"
          }
        ],
        "responses": {
          "200": {
            "description": "OK"
          }
        }
      }
    },
    "/weather/detailsByLocation": {
      "get": {
        "description": "",
        "parameters": [
          {
            "name": "lat",
            "in": "query",
            "type": "string"
          },
          {
            "name": "lon",
            "in": "query",
            "type": "string"
          },
          {
            "name": "units",
            "in": "query",
            "type": "string"
          }
        ],
        "responses": {
          "200": {
            "description": "OK"
          }
        }
      }
    }
  }
}